{
  "id": "3150",
  "name": "웨리",
  "name_en": "Wheri",
  "grade": "에픽",
  "race": "요정형",
  "class": "서포터",
  "sub_class": "보호",
  "stat": "지능",
  "profile": {
    "nick_name": "라플라스의 관측자",
    "constellation": "인연_제이드_이벤트1",
    "union": "페이렌 연합국",
    "birthday": "512",
    "height": 169,
    "weight": null,
    "cv_ko": "홍수정",
    "cv_jp": "Ohnishi Ayaka",
    "like": [
      "생물"
    ],
    "dislike": [
      "잠"
    ],
    "hobby": [
      "뜨개질"
    ],
    "speciality": [
      "미래 예측"
    ]
  },
  "personality": {
    "description": "만나서 반가워요, 구원자.",
    "greeting": "페이렌의 대현자, 웨리입니다."
  },
  "speech_patterns": [
    "반가워요, 구원자.",
    "당신의 연락처라고 들었는데 맞나요?",
    "후후… 페이렌의 대현자 웨리예요.",
    "잘 연락이 닿아서 다행이네요.",
    "당신이 있는 곳은 잘 읽히지 않아서 확신이 없었는데… ",
    "아녜요.",
    "앞으로 잘 부탁해요.",
    "구원자.",
    "네, 무슨 일이시죠?",
    "조금",
    "황당한 이야기네요.",
    "좀 더 자세히 말해주시겠어요?",
    "후후… 구원자.",
    "물론 개구리는 고양이와 달라요.",
    "하지만 개구리도 마음에 드는 일이 있을 땐 꽤 적극적이랍니다.",
    "개구리가 구원자를 마음에 들어 했나 봐요.",
    "다른 아이들도 구원자에게 말 걸지도 모르니",
    "주변을 주의 깊게 둘러보세요.",
    "구원자,",
    "좋아하는 차가 있으신가요?",
    "구원자가 찾아올 때를 대비해 미리 준비해 두려고요.",
    "제 온실의 첫 손님인데 좋은 차로 대접하고 싶어요.",
    "이런…",
    "저… 조금 들뜬 것 같네요.",
    "이런 경우가 별로 없는데, ",
    "어머, 반가운 이야기네요.",
    "하지만 무리는 하지 말아주세요.",
    "구원자, 라우라를 만나셨나요?",
    "어떠셨나요? ",
    "라우라가 그러던가요?",
    "그건 라우라의 개인적인 취미예요.",
    "페이렌 정령들은 숲에서 다양한 놀이를 하지만,",
    "그 아이처럼 특이한 취향은 드물어요.",
    "혹시 '구덩이 놀이'에 관심이 생기신 거라면… ",
    "제가 라우라에게 전달해 줄게요.",
    "부작용이 사라진다면요?",
    "음… 그럴 일은 없겠지만",
    "만약 사라진다면 일출을 보고 싶어요.",
    "네, 해가 떠오르기 시작하면",
    "동물들이 잠에서 깨어나 머릿속이 복잡해지거든요.",
    "그래서 항상 해가 완전히 떠오르는 걸 천천히… ",
    "아주 느긋하게 보고 싶다고 생각했어요.",
    "아름다운 페이렌 숲이 깨어나는걸",
    "처음부터 끝까지 지켜보는 거죠.",
    "고마워요.",
    "언젠가 보게 된다면,",
    "당신께 꼭 감상을 알려드릴게요.",
    "마물 토벌이 어느 정도 정리가 되면",
    "가보고 싶은 곳이 있나요?",
    "그래도 페이렌까지 와주셨는데"
  ],
  "comments": [
    {
      "writer": "아야메",
      "comment": "손재주가 몹시 좋은 분이라고 들었사옵니다. 함께 매듭을 만들어보고 싶사와요."
    },
    {
      "writer": "탈리아",
      "comment": "나랑은 다른 방식으로 운명을 읽을 수 있는 정령이야. 어떤 미래를 보고 있는 걸까?"
    },
    {
      "writer": "도미니크",
      "comment": "무, 무척 다정한 분이세요. 하, 하지만 가끔… 무, 무서워요… 왜 그럴까요…?"
    }
  ],
  "dialogues": {
    "story": [],
    "evertalk": [
      {
        "speaker": "웨리",
        "message": "반가워요, 구원자."
      },
      {
        "speaker": "웨리",
        "message": "당신의 연락처라고 들었는데 맞나요?"
      },
      {
        "speaker": "구원자",
        "message": "맞아."
      },
      {
        "speaker": "구원자",
        "message": "맞아."
      },
      {
        "speaker": "구원자",
        "message": "누구야?"
      },
      {
        "speaker": "구원자",
        "message": "누구야?"
      },
      {
        "speaker": "웨리",
        "message": "후후… 페이렌의 대현자 웨리예요."
      },
      {
        "speaker": "웨리",
        "message": "잘 연락이 닿아서 다행이네요."
      },
      {
        "speaker": "웨리",
        "message": "당신이 있는 곳은 잘 읽히지 않아서 확신이 없었는데… "
      },
      {
        "speaker": "구원자",
        "message": "읽히지 않는다고?"
      },
      {
        "speaker": "구원자",
        "message": "읽히지 않는다고?"
      },
      {
        "speaker": "웨리",
        "message": "아녜요."
      },
      {
        "speaker": "웨리",
        "message": "앞으로 잘 부탁해요."
      },
      {
        "speaker": "웨리",
        "message": "구원자."
      },
      {
        "speaker": "구원자",
        "message": "나도 잘 부탁해"
      },
      {
        "speaker": "구원자",
        "message": "나도 잘 부탁해"
      },
      {
        "speaker": "구원자",
        "message": "웨리, 혹시… "
      },
      {
        "speaker": "구원자",
        "message": "웨리, 혹시… "
      },
      {
        "speaker": "웨리",
        "message": "네, 무슨 일이시죠?"
      },
      {
        "speaker": "구원자",
        "message": "혹시 페이렌에서 개구리는"
      },
      {
        "speaker": "구원자",
        "message": "혹시 페이렌에서 개구리는"
      },
      {
        "speaker": "구원자",
        "message": "길고양이 같은 존재야…?"
      },
      {
        "speaker": "구원자",
        "message": "길고양이 같은 존재야…?"
      },
      {
        "speaker": "웨리",
        "message": "조금"
      },
      {
        "speaker": "웨리",
        "message": "황당한 이야기네요."
      },
      {
        "speaker": "웨리",
        "message": "좀 더 자세히 말해주시겠어요?"
      },
      {
        "speaker": "구원자",
        "message": "개구리가 날 막 따라오고"
      },
      {
        "speaker": "구원자",
        "message": "개구리가 날 막 따라오고"
      },
      {
        "speaker": "구원자",
        "message": "날 부르고"
      },
      {
        "speaker": "구원자",
        "message": "날 부르고"
      },
      {
        "speaker": "구원자",
        "message": "자길 따라오라고 했어"
      },
      {
        "speaker": "구원자",
        "message": "자길 따라오라고 했어"
      },
      {
        "speaker": "구원자",
        "message": "보통 개구리는 안 그렇잖아"
      },
      {
        "speaker": "구원자",
        "message": "보통 개구리는 안 그렇잖아"
      },
      {
        "speaker": "웨리",
        "message": "후후… 구원자."
      },
      {
        "speaker": "웨리",
        "message": "물론 개구리는 고양이와 달라요."
      },
      {
        "speaker": "웨리",
        "message": "하지만 개구리도 마음에 드는 일이 있을 땐 꽤 적극적이랍니다."
      },
      {
        "speaker": "웨리",
        "message": "개구리가 구원자를 마음에 들어 했나 봐요."
      },
      {
        "speaker": "웨리",
        "message": "다른 아이들도 구원자에게 말 걸지도 모르니"
      },
      {
        "speaker": "웨리",
        "message": "주변을 주의 깊게 둘러보세요."
      },
      {
        "speaker": "구원자",
        "message": "갑자기 사방에서 날 감시하는 듯한 기분이… "
      },
      {
        "speaker": "구원자",
        "message": "갑자기 사방에서 날 감시하는 듯한 기분이… "
      },
      {
        "speaker": "웨리",
        "message": "구원자,"
      },
      {
        "speaker": "웨리",
        "message": "좋아하는 차가 있으신가요?"
      },
      {
        "speaker": "웨리",
        "message": "구원자가 찾아올 때를 대비해 미리 준비해 두려고요."
      },
      {
        "speaker": "구원자",
        "message": "난 아무거나 괜찮은데… "
      },
      {
        "speaker": "구원자",
        "message": "난 아무거나 괜찮은데… "
      },
      {
        "speaker": "구원자",
        "message": "신경 써줘서 고마워"
      },
      {
        "speaker": "구원자",
        "message": "신경 써줘서 고마워"
      },
      {
        "speaker": "웨리",
        "message": "아녜요."
      },
      {
        "speaker": "웨리",
        "message": "제 온실의 첫 손님인데 좋은 차로 대접하고 싶어요."
      },
      {
        "speaker": "웨리",
        "message": "이런…"
      },
      {
        "speaker": "웨리",
        "message": "저… 조금 들뜬 것 같네요."
      },
      {
        "speaker": "웨리",
        "message": "이런 경우가 별로 없는데, "
      },
      {
        "speaker": "구원자",
        "message": "웨리… "
      },
      {
        "speaker": "구원자",
        "message": "웨리… "
      },
      {
        "speaker": "구원자",
        "message": "내가 시간 나면 종종 찾아갈게"
      },
      {
        "speaker": "구원자",
        "message": "내가 시간 나면 종종 찾아갈게"
      },
      {
        "speaker": "웨리",
        "message": "어머, 반가운 이야기네요."
      },
      {
        "speaker": "웨리",
        "message": "하지만 무리는 하지 말아주세요."
      },
      {
        "speaker": "웨리",
        "message": "구원자, 라우라를 만나셨나요?"
      },
      {
        "speaker": "구원자",
        "message": "응, 만났어"
      },
      {
        "speaker": "구원자",
        "message": "응, 만났어"
      },
      {
        "speaker": "웨리",
        "message": "어떠셨나요? "
      },
      {
        "speaker": "구원자",
        "message": "좀 특이했어"
      },
      {
        "speaker": "구원자",
        "message": "좀 특이했어"
      },
      {
        "speaker": "구원자",
        "message": "흥미로운 구덩이가 있으면 뛰어든다고 하던데… "
      },
      {
        "speaker": "구원자",
        "message": "흥미로운 구덩이가 있으면 뛰어든다고 하던데… "
      },
      {
        "speaker": "구원자",
        "message": "페이렌 정령들은 원래 구덩이에서 놀아?"
      },
      {
        "speaker": "구원자",
        "message": "페이렌 정령들은 원래 구덩이에서 놀아?"
      },
      {
        "speaker": "웨리",
        "message": "라우라가 그러던가요?"
      },
      {
        "speaker": "웨리",
        "message": "그건 라우라의 개인적인 취미예요."
      },
      {
        "speaker": "웨리",
        "message": "페이렌 정령들은 숲에서 다양한 놀이를 하지만,"
      },
      {
        "speaker": "웨리",
        "message": "그 아이처럼 특이한 취향은 드물어요."
      },
      {
        "speaker": "구원자",
        "message": "정말 특이하네"
      },
      {
        "speaker": "구원자",
        "message": "정말 특이하네"
      },
      {
        "speaker": "웨리",
        "message": "혹시 '구덩이 놀이'에 관심이 생기신 거라면… "
      },
      {
        "speaker": "웨리",
        "message": "제가 라우라에게 전달해 줄게요."
      },
      {
        "speaker": "구원자",
        "message": "아냐 괜찮아;"
      },
      {
        "speaker": "구원자",
        "message": "아냐 괜찮아;"
      },
      {
        "speaker": "구원자",
        "message": "웨리, 만약 능력의 부작용이 사라진다면… "
      },
      {
        "speaker": "구원자",
        "message": "웨리, 만약 능력의 부작용이 사라진다면… "
      },
      {
        "speaker": "구원자",
        "message": "제일 해보고 싶은 게 뭐야?"
      },
      {
        "speaker": "구원자",
        "message": "제일 해보고 싶은 게 뭐야?"
      },
      {
        "speaker": "웨리",
        "message": "부작용이 사라진다면요?"
      },
      {
        "speaker": "웨리",
        "message": "음… 그럴 일은 없겠지만"
      },
      {
        "speaker": "웨리",
        "message": "만약 사라진다면 일출을 보고 싶어요."
      },
      {
        "speaker": "구원자",
        "message": "일출을?"
      },
      {
        "speaker": "구원자",
        "message": "일출을?"
      },
      {
        "speaker": "웨리",
        "message": "네, 해가 떠오르기 시작하면"
      },
      {
        "speaker": "웨리",
        "message": "동물들이 잠에서 깨어나 머릿속이 복잡해지거든요."
      },
      {
        "speaker": "웨리",
        "message": "그래서 항상 해가 완전히 떠오르는 걸 천천히… "
      },
      {
        "speaker": "웨리",
        "message": "아주 느긋하게 보고 싶다고 생각했어요."
      },
      {
        "speaker": "웨리",
        "message": "아름다운 페이렌 숲이 깨어나는걸"
      },
      {
        "speaker": "웨리",
        "message": "처음부터 끝까지 지켜보는 거죠."
      },
      {
        "speaker": "구원자",
        "message": "정말 멋진 풍경이겠다… "
      },
      {
        "speaker": "구원자",
        "message": "정말 멋진 풍경이겠다… "
      },
      {
        "speaker": "구원자",
        "message": "언젠가 볼 수 있으면 좋겠네"
      },
      {
        "speaker": "구원자",
        "message": "언젠가 볼 수 있으면 좋겠네"
      },
      {
        "speaker": "웨리",
        "message": "고마워요."
      },
      {
        "speaker": "웨리",
        "message": "언젠가 보게 된다면,"
      },
      {
        "speaker": "웨리",
        "message": "당신께 꼭 감상을 알려드릴게요."
      },
      {
        "speaker": "웨리",
        "message": "구원자,"
      },
      {
        "speaker": "웨리",
        "message": "마물 토벌이 어느 정도 정리가 되면"
      },
      {
        "speaker": "웨리",
        "message": "가보고 싶은 곳이 있나요?"
      },
      {
        "speaker": "웨리",
        "message": "그래도 페이렌까지 와주셨는데"
      },
      {
        "speaker": "웨리",
        "message": "궁금한 곳이 있다면 안내해 드릴게요."
      },
      {
        "speaker": "구원자",
        "message": "글쎄…"
      },
      {
        "speaker": "구원자",
        "message": "글쎄…"
      },
      {
        "speaker": "구원자",
        "message": "페이렌에 관광할 만한 곳이 있어?"
      },
      {
        "speaker": "구원자",
        "message": "페이렌에 관광할 만한 곳이 있어?"
      },
      {
        "speaker": "웨리",
        "message": "음… 글쎄요."
      },
      {
        "speaker": "웨리",
        "message": "북부 지역의 온천이 인기가 많은 편이죠."
      },
      {
        "speaker": "구원자",
        "message": "온천이 있었어?"
      },
      {
        "speaker": "구원자",
        "message": "온천이 있었어?"
      },
      {
        "speaker": "웨리",
        "message": "네, 화산이 있거든요."
      },
      {
        "speaker": "구원자",
        "message": "화산 온천이라니 신기하다~"
      },
      {
        "speaker": "구원자",
        "message": "화산 온천이라니 신기하다~"
      },
      {
        "speaker": "구원자",
        "message": "다음에 같이 가보자"
      },
      {
        "speaker": "구원자",
        "message": "다음에 같이 가보자"
      },
      {
        "speaker": "웨리",
        "message": "후후… 좋아요."
      },
      {
        "speaker": "웨리",
        "message": "온천을 같이 가지고 말해준 것도 구원자가 처음이에요."
      },
      {
        "speaker": "웨리",
        "message": "구원자는 대담한 면이 있으시네요."
      },
      {
        "speaker": "웨리",
        "message": "구원자의 수영복… 기대할게요."
      },
      {
        "speaker": "구원자",
        "message": "잠깐, 같이 들어가게?!"
      },
      {
        "speaker": "구원자",
        "message": "잠깐, 같이 들어가게?!"
      },
      {
        "speaker": "구원자",
        "message": "난 당연히 따로 들어가는 줄 알고…!"
      },
      {
        "speaker": "구원자",
        "message": "난 당연히 따로 들어가는 줄 알고…!"
      },
      {
        "speaker": "구원자",
        "message": "웨리…?!"
      },
      {
        "speaker": "구원자",
        "message": "웨리…?!"
      },
      {
        "speaker": "구원자",
        "message": "식사 도중에 나가서 미안해… "
      },
      {
        "speaker": "구원자",
        "message": "식사 도중에 나가서 미안해… "
      },
      {
        "speaker": "웨리",
        "message": "괜찮아요."
      },
      {
        "speaker": "웨리",
        "message": "급한 일이 있으셨던 것 같던데"
      },
      {
        "speaker": "웨리",
        "message": "신경 쓰지 마세요."
      },
      {
        "speaker": "구원자",
        "message": "아냐 미안… "
      },
      {
        "speaker": "구원자",
        "message": "아냐 미안… "
      },
      {
        "speaker": "구원자",
        "message": "그런데 "
      },
      {
        "speaker": "구원자",
        "message": "그런데 "
      },
      {
        "speaker": "구원자",
        "message": "웨리도 거의 먹지 않은 것 같던데"
      },
      {
        "speaker": "구원자",
        "message": "웨리도 거의 먹지 않은 것 같던데"
      },
      {
        "speaker": "구원자",
        "message": "무슨 일 있어?"
      },
      {
        "speaker": "구원자",
        "message": "무슨 일 있어?"
      },
      {
        "speaker": "웨리",
        "message": "아… "
      },
      {
        "speaker": "웨리",
        "message": "저는 원래 잘 못 먹어요."
      },
      {
        "speaker": "구원자",
        "message": "이유가 있는 거야?"
      },
      {
        "speaker": "구원자",
        "message": "이유가 있는 거야?"
      },
      {
        "speaker": "웨리",
        "message": "이유라…"
      },
      {
        "speaker": "웨리",
        "message": "아마 구원자를 포함한 다른 정령들은 느끼지 못하겠지만"
      },
      {
        "speaker": "웨리",
        "message": "저는 식재료가 제 식탁에 올라올 때까지"
      },
      {
        "speaker": "웨리",
        "message": "어떤 삶을 살았는지 전부 보여서 말이죠."
      },
      {
        "speaker": "웨리",
        "message": "식사 때마다 정보량이 너무 많아져 힘들어요."
      },
      {
        "speaker": "구원자",
        "message": "그거 힘들겠네… "
      },
      {
        "speaker": "구원자",
        "message": "그거 힘들겠네… "
      },
      {
        "speaker": "웨리",
        "message": "너무 안타까워하지 마세요."
      },
      {
        "speaker": "웨리",
        "message": "나름 재밌는 사실도 알게 되거든요."
      },
      {
        "speaker": "웨리",
        "message": "그거 아시나요, 구원자?"
      },
      {
        "speaker": "웨리",
        "message": "생물이 어떤 삶을 살았는지에 따라 맛이 전부 달라요."
      },
      {
        "speaker": "웨리",
        "message": "기나긴 삶이 쌓여서 '맛'으로 나타나는 것이죠."
      },
      {
        "speaker": "웨리",
        "message": "그래서 음식을 입으로 씹다 보면… "
      },
      {
        "speaker": "구원자",
        "message": "으악! 잠깐!"
      },
      {
        "speaker": "구원자",
        "message": "으악! 잠깐!"
      },
      {
        "speaker": "구원자",
        "message": "이 이상은 들으면 안 될 것 같아!"
      },
      {
        "speaker": "구원자",
        "message": "이 이상은 들으면 안 될 것 같아!"
      },
      {
        "speaker": "웨리",
        "message": "구원자는 어떻게 아케나인의 영주가 됐나요?"
      },
      {
        "speaker": "구원자",
        "message": "나? 나는… "
      },
      {
        "speaker": "구원자",
        "message": "나? 나는… "
      },
      {
        "speaker": "구원자",
        "message": "유리아의 제안으로 영주가 됐어"
      },
      {
        "speaker": "구원자",
        "message": "유리아의 제안으로 영주가 됐어"
      },
      {
        "speaker": "구원자",
        "message": "웨리는 어떻게 대현자가 된 거야?"
      },
      {
        "speaker": "구원자",
        "message": "웨리는 어떻게 대현자가 된 거야?"
      },
      {
        "speaker": "웨리",
        "message": "후후… 제 이야기도 궁금하신가요?"
      },
      {
        "speaker": "구원자",
        "message": "말하기 어렵다면 말 안 해줘도 괜찮아"
      },
      {
        "speaker": "구원자",
        "message": "말하기 어렵다면 말 안 해줘도 괜찮아"
      },
      {
        "speaker": "웨리",
        "message": "아녜요."
      },
      {
        "speaker": "웨리",
        "message": "저에 대해 궁금하셨다니 기쁜걸요."
      },
      {
        "speaker": "웨리",
        "message": "저는, 선대 대현자님 밑에서 일하는 정령 중 하나였어요."
      },
      {
        "speaker": "웨리",
        "message": "그러던 어느 날"
      },
      {
        "speaker": "웨리",
        "message": "한 악마형 정령의 폭주로 한 마을 전체가 오염되는 큰 사건이 일어났어요."
      },
      {
        "speaker": "웨리",
        "message": "그 오염 속도가 어찌나 빠른지"
      },
      {
        "speaker": "웨리",
        "message": "마을 뿐만 아니라 그 주변 숲까지 모두 집어삼켰죠."
      },
      {
        "speaker": "웨리",
        "message": "그대로 두었다간 페이렌 숲이 망가질 것 같아"
      },
      {
        "speaker": "웨리",
        "message": "제 개인적인 판단으로 마을과 숲, 미처 도망치지 못한 정령까지"
      },
      {
        "speaker": "웨리",
        "message": "통째로 봉인시켰어요."
      },
      {
        "speaker": "웨리",
        "message": "대현자님께 허락도 받지 않고 제 개인적인 판단으로 말이죠."
      },
      {
        "speaker": "웨리",
        "message": "그 뒤로 선대 대현자님께서 절 눈여겨보시더니"
      },
      {
        "speaker": "웨리",
        "message": "후대 대현자로 추천하시더군요."
      },
      {
        "speaker": "구원자",
        "message": "웨리가 좋은 판단을 내렸나 보네."
      },
      {
        "speaker": "구원자",
        "message": "웨리가 좋은 판단을 내렸나 보네."
      },
      {
        "speaker": "웨리",
        "message": "그 상황에서 최선의 판단을 내렸을 뿐."
      },
      {
        "speaker": "웨리",
        "message": "좋은 판단인지는 모르겠네요."
      },
      {
        "speaker": "구원자",
        "message": "최선의 판단이"
      },
      {
        "speaker": "구원자",
        "message": "최선의 판단이"
      },
      {
        "speaker": "구원자",
        "message": "언제나 좋은 판단이 되는 건 아니지… "
      },
      {
        "speaker": "구원자",
        "message": "언제나 좋은 판단이 되는 건 아니지… "
      },
      {
        "speaker": "웨리",
        "message": "역시 구원자는 이해하시는군요."
      },
      {
        "speaker": "웨리",
        "message": "고마워요."
      },
      {
        "speaker": "웨리",
        "message": "제 첫인상을 알려줘요, 구원자."
      },
      {
        "speaker": "구원자",
        "message": "웨리의 첫인상은… "
      },
      {
        "speaker": "구원자",
        "message": "웨리의 첫인상은… "
      },
      {
        "speaker": "구원자",
        "message": "기계 같다고 생각했어."
      },
      {
        "speaker": "구원자",
        "message": "기계 같다고 생각했어."
      },
      {
        "speaker": "웨리",
        "message": "잘 파악하셨네요."
      },
      {
        "speaker": "구원자",
        "message": "내 첫인상은 어땠어?"
      },
      {
        "speaker": "구원자",
        "message": "내 첫인상은 어땠어?"
      },
      {
        "speaker": "웨리",
        "message": "구원자의 첫인상이요?"
      },
      {
        "speaker": "웨리",
        "message": "당신을 알게 된 순간부터 "
      },
      {
        "speaker": "웨리",
        "message": "그 이후 펼쳐질 미래의 가능성을 보느라"
      },
      {
        "speaker": "웨리",
        "message": "사실 구원자에 대한 첫인상은 흐릿해요."
      },
      {
        "speaker": "웨리",
        "message": "하지만 온실에 찾아온 당신을 처음 봤을 땐,"
      },
      {
        "speaker": "웨리",
        "message": "솔직히 좋은 분이라고 생각했어요."
      },
      {
        "speaker": "웨리",
        "message": "제가 상상한 것 보다 좀 더."
      },
      {
        "speaker": "웨리",
        "message": "이런 것도 첫인상으로 쳐주시나요?"
      },
      {
        "speaker": "구원자",
        "message": "응. 쳐줄게."
      },
      {
        "speaker": "구원자",
        "message": "응. 쳐줄게."
      },
      {
        "speaker": "구원자",
        "message": "좋게 봐줘서 고마워"
      },
      {
        "speaker": "구원자",
        "message": "좋게 봐줘서 고마워"
      },
      {
        "speaker": "웨리",
        "message": "당신이 잠든 걸 본 적 있어요."
      },
      {
        "speaker": "웨리",
        "message": "정확히 말하자면 '보인'거죠."
      },
      {
        "speaker": "웨리",
        "message": "참고로 전 누군가가 잠든 모습을 구경하는 취미는 없어요."
      },
      {
        "speaker": "웨리",
        "message": "수면에 대한 관심도 없고요."
      },
      {
        "speaker": "웨리",
        "message": "하지만 구원자가 잠든 모습을 보니,"
      },
      {
        "speaker": "웨리",
        "message": "어쩐지 옆에서 계속 바라보고 싶다는 생각이 들었어요."
      },
      {
        "speaker": "구원자",
        "message": "내가 잠든 모습을…?"
      },
      {
        "speaker": "구원자",
        "message": "내가 잠든 모습을…?"
      },
      {
        "speaker": "웨리",
        "message": "규칙적으로 오르락내리락하는 몸과"
      },
      {
        "speaker": "웨리",
        "message": "가끔씩 움찔거리는 표정을 보면서… "
      },
      {
        "speaker": "웨리",
        "message": "구원자가 눈을 떠 저를 바라봐줄 때까지"
      },
      {
        "speaker": "웨리",
        "message": "그저 조용히 바라보고 싶다는 생각이 들었어요."
      },
      {
        "speaker": "웨리",
        "message": "…그냥, 그렇다고요."
      },
      {
        "speaker": "웨리",
        "message": "토벌 작전을 도와주셔서 감사해요."
      },
      {
        "speaker": "웨리",
        "message": "페이렌에 머무는 동안 편히 지내주세요."
      },
      {
        "speaker": "웨리",
        "message": "그럼, 이만."
      },
      {
        "speaker": "웨리",
        "message": "구원자."
      },
      {
        "speaker": "웨리",
        "message": "제 온실로 오는 길은 잘 기억하고 있죠?"
      },
      {
        "speaker": "구원자",
        "message": "응, 잘 기억하고 있어"
      },
      {
        "speaker": "구원자",
        "message": "응, 잘 기억하고 있어"
      },
      {
        "speaker": "웨리",
        "message": "좋아요."
      },
      {
        "speaker": "웨리",
        "message": "제가 필요해지면…"
      },
      {
        "speaker": "웨리",
        "message": "그 길을 따라와 주세요."
      },
      {
        "speaker": "웨리",
        "message": "전 언제나 이곳에 있으니까요."
      },
      {
        "speaker": "구원자",
        "message": "웨리, 뜨개질 좋아해?"
      },
      {
        "speaker": "구원자",
        "message": "웨리, 뜨개질 좋아해?"
      },
      {
        "speaker": "웨리",
        "message": "후후… 제 뜨개질 바구니를 보셨군요?"
      },
      {
        "speaker": "웨리",
        "message": "네, 맞아요."
      },
      {
        "speaker": "웨리",
        "message": "최근 뜨개질에 푹 빠져있답니다."
      },
      {
        "speaker": "구원자",
        "message": "잘하는 편이야?"
      },
      {
        "speaker": "구원자",
        "message": "잘하는 편이야?"
      },
      {
        "speaker": "웨리",
        "message": "제가 뜨개질을 몇 년이나 했는지 알게 된다면"
      },
      {
        "speaker": "웨리",
        "message": "깜짝 놀라실걸요."
      },
      {
        "speaker": "웨리",
        "message": "주변에 있는 것들은 대부분 만들 수 있어요."
      },
      {
        "speaker": "구원자",
        "message": "우와…"
      },
      {
        "speaker": "구원자",
        "message": "우와…"
      },
      {
        "speaker": "구원자",
        "message": "정말 뜨개질을 좋아하는구나"
      },
      {
        "speaker": "구원자",
        "message": "정말 뜨개질을 좋아하는구나"
      },
      {
        "speaker": "구원자",
        "message": "그렇다면… "
      },
      {
        "speaker": "구원자",
        "message": "그렇다면… "
      },
      {
        "speaker": "구원자",
        "message": "나 좀 가르쳐줄래?"
      },
      {
        "speaker": "구원자",
        "message": "나 좀 가르쳐줄래?"
      },
      {
        "speaker": "웨리",
        "message": "좋아요."
      },
      {
        "speaker": "웨리",
        "message": "당신의 부탁인데 거절할 이유가 없죠."
      },
      {
        "speaker": "웨리",
        "message": "구원자,"
      },
      {
        "speaker": "웨리",
        "message": "요즘 악몽은 어떠신가요?"
      },
      {
        "speaker": "구원자",
        "message": "많이 좋아졌어"
      },
      {
        "speaker": "구원자",
        "message": "많이 좋아졌어"
      },
      {
        "speaker": "웨리",
        "message": "그런가요?"
      },
      {
        "speaker": "웨리",
        "message": "하지만 당신 얼굴은…"
      },
      {
        "speaker": "웨리",
        "message": "전보다 더 피곤해 보여요."
      },
      {
        "speaker": "웨리",
        "message": "구원자, 잘 들어갔나요?"
      },
      {
        "speaker": "웨리",
        "message": "지난번에 하던 이야기를 마저 하고 싶어요."
      },
      {
        "speaker": "웨리",
        "message": "시간 나면 온실에 찾아와주세요."
      },
      {
        "speaker": "웨리",
        "message": "기다리고 있을게요."
      },
      {
        "speaker": "웨리",
        "message": "지난밤엔 온실에 오지 않으셨네요."
      },
      {
        "speaker": "웨리",
        "message": "악몽이 사라지셨나요?"
      },
      {
        "speaker": "웨리",
        "message": "아니면 혹시 절 보기 어려우셨나요?"
      },
      {
        "speaker": "웨리",
        "message": "이유가 무엇이든 괜찮아요."
      },
      {
        "speaker": "웨리",
        "message": "오늘 식사 시간에 늦지 않게 와주세요."
      },
      {
        "speaker": "웨리",
        "message": "기다리고 있을게요."
      },
      {
        "speaker": "웨리",
        "message": "구원자."
      },
      {
        "speaker": "웨리",
        "message": "구원자?"
      },
      {
        "speaker": "웨리",
        "message": "잠드셨나요?"
      },
      {
        "speaker": "웨리",
        "message": "그곳의 저를 만나러 떠나셨나요?"
      },
      {
        "speaker": "웨리",
        "message": "그렇다면 저도… "
      },
      {
        "speaker": "웨리",
        "message": "당신을 마중 나갈게요."
      },
      {
        "speaker": "웨리",
        "message": "구원자는 운명을 믿으시나요?"
      },
      {
        "speaker": "웨리",
        "message": "운명은 믿고 말고 할 수 있는 게 아니죠."
      },
      {
        "speaker": "웨리",
        "message": "우리는 모두 운명이라는 질긴 실 위에 서 있으니까요."
      },
      {
        "speaker": "웨리",
        "message": "일어날 미래는 일어날 것이고,"
      },
      {
        "speaker": "웨리",
        "message": "아무리 원망하고 애원해도 과거는 변하지 않죠."
      },
      {
        "speaker": "웨리",
        "message": "그러니 구원자, "
      },
      {
        "speaker": "웨리",
        "message": "절 원망하고 미워해 주세요."
      },
      {
        "speaker": "웨리",
        "message": "그 또한 우리의 운명이니까요."
      },
      {
        "speaker": "웨리",
        "message": "구원자, 제게 졸음이 찾아왔어요."
      },
      {
        "speaker": "웨리",
        "message": "이제 곧 겨울이군요."
      },
      {
        "speaker": "웨리",
        "message": "약속한 시간이 끝나간다는 뜻이겠죠."
      },
      {
        "speaker": "웨리",
        "message": "구원자."
      },
      {
        "speaker": "웨리",
        "message": "수고했어요."
      },
      {
        "speaker": "웨리",
        "message": "구원자, 오고 계신가요?"
      },
      {
        "speaker": "웨리",
        "message": "오늘 나이아를 페이렌에 초대했어요."
      },
      {
        "speaker": "웨리",
        "message": "당신이 알려준 방법을 사용해 볼 예정이에요."
      },
      {
        "speaker": "웨리",
        "message": "제가 잘할 수 있을까요?"
      },
      {
        "speaker": "웨리",
        "message": "사랑스러운 나의 구원자,"
      },
      {
        "speaker": "웨리",
        "message": "사랑의 날인데… 절 혼자 두진 않으실 거죠?"
      },
      {
        "speaker": "구원자",
        "message": "가는 중이야, 웨리!"
      },
      {
        "speaker": "구원자",
        "message": "가는 중이야, 웨리!"
      },
      {
        "speaker": "웨리",
        "message": "새 생명이 피어나는 날을 축하해요."
      },
      {
        "speaker": "웨리",
        "message": "구원자에게 행복이 가득하길."
      },
      {
        "speaker": "구원자",
        "message": "웨리도 행복하길"
      },
      {
        "speaker": "구원자",
        "message": "웨리도 행복하길"
      },
      {
        "speaker": "웨리",
        "message": "이제 올해도 끝나가네요."
      },
      {
        "speaker": "웨리",
        "message": "올해도 당신과 함께해서 더 특별했어요."
      },
      {
        "speaker": "구원자",
        "message": "나도, 웨리와 함께해서 좋았어."
      },
      {
        "speaker": "구원자",
        "message": "나도, 웨리와 함께해서 좋았어."
      }
    ]
  }
}